[
  {
    "Wat is je favoriete soort huisdier?": "kat",
    "Wat is je oogkleur?": "Bruin",
    "Wat is je favoriete windrichting?": "Oost",
    "Op een schaal van 1 tot 10, hoeveel zin heb je in de Tech Track?": 7,
    "Kies zelf of je deze vraag beantwoord.": "Oke",
    "Wat is je favoriete datum?": "15/01/1999",
    "Wat is je favoriete datum, maar nu in tekst!": "vijftien januari negentiennegenennegentig",
    "Wat is je favoriete zuivelproduct?": "Melk",
    "Welke kleur kledingstukken heb je aan vandaag? (Meerdere antwoorden mogelijk natuurlijk...)": "Zwart, Grijs",
    "Op welke verdieping van het TTH studeer je het liefst?": 2,
    "Wat wil je worden als je groot bent?": "Frontend developer",
    "Wat wilde je later worden als je groot bent, maar nu toen je zelf 8 jaar was.": "Piloot",
    "Kaas is ook een zoogdier?": "Wat.",
    "Als je later een auto zou kopen, van welk merk zou deze dan zijn?": "Mercedes C63 AMG"
  },
  {
    "Wat is je favoriete soort huisdier?": "hond",
    "Wat is je oogkleur?": "blauw",
    "Wat is je favoriete windrichting?": "Zuid",
    "Op een schaal van 1 tot 10, hoeveel zin heb je in de Tech Track?": 7,
    "Kies zelf of je deze vraag beantwoord.": "",
    "Wat is je favoriete datum?": "2021-02-09",
    "Wat is je favoriete datum, maar nu in tekst!": "7 juni 2002",
    "Wat is je favoriete zuivelproduct?": "Kaas",
    "Welke kleur kledingstukken heb je aan vandaag? (Meerdere antwoorden mogelijk natuurlijk...)": "Blauw, Zwart",
    "Op welke verdieping van het TTH studeer je het liefst?": 4,
    "Wat wil je worden als je groot bent?": "Gelukkig",
    "Wat wilde je later worden als je groot bent, maar nu toen je zelf 8 jaar was.": "Gelukkig",
    "Kaas is ook een zoogdier?": "",
    "Als je later een auto zou kopen, van welk merk zou deze dan zijn?": "Tesla"
  }
]